README.rst
setup.py
record_ip_to_dnspod/__init__.py
record_ip_to_dnspod/bin.py
record_ip_to_dnspod/compat.py
record_ip_to_dnspod/dnspod.py
record_ip_to_dnspod/ip_addr.py
record_ip_to_dnspod.egg-info/PKG-INFO
record_ip_to_dnspod.egg-info/SOURCES.txt
record_ip_to_dnspod.egg-info/dependency_links.txt
record_ip_to_dnspod.egg-info/entry_points.txt
record_ip_to_dnspod.egg-info/top_level.txt