Metadata-Version: 1.0
Name: record-ip-to-dnspod
Version: 0.1.1
Summary: Record IP Via DNSPod API.
Home-page: https://github.com/codeif/record-ip-to-dnspod
Author: codeif
Author-email: me@codeif.com
License: MIT
Platform: UNKNOWN
